pygameforbabies/__init__.py
pygameforbabies/clipboard.py
pygameforbabies/connect.py
pygameforbabies/d3.py
pygameforbabies/keys.py
pygameforbabies/log.py
pygameforbabies/mouses.py
pygameforbabies/window.py
pygameforbabies-0.0.8.dist-info/licenses/LICENSE
pygameforbabies-0.0.8.dist-info/METADATA
pygameforbabies-0.0.8.dist-info/WHEEL
pygameforbabies-0.0.8.dist-info/top_level.txt
pygameforbabies-0.0.8.dist-info/RECORD
