Metadata-Version: 2.4
Name: pygameforbabies
Version: 0.0.8
Summary: simple pygame
Author-email: Annes <anneswidow@gmail.com>
License-Expression: MIT
Requires-Python: >=3.7
License-File: LICENSE
Dynamic: license-file
